currency_converter_with_rate/__init__.py
currency_converter_with_rate/api.py
currency_converter_with_rate/converter.py
currency_converter_with_rate/currency.py
currency_converter_with_rate/currency_rates.py
currency_converter_with_rate/rates.py
currency_converter_with_rate-1.1.0.dist-info/LICENSE
currency_converter_with_rate-1.1.0.dist-info/METADATA
currency_converter_with_rate-1.1.0.dist-info/WHEEL
currency_converter_with_rate-1.1.0.dist-info/top_level.txt
currency_converter_with_rate-1.1.0.dist-info/RECORD
