Metadata-Version: 2.1
Name: currency-converter-with-rate
Version: 1.1.0
Summary: Currency conversion between any two or to multiple and currency rates based on some parameters
Home-page: https://github.com/NazemMahmud/currencyConverterWithRate
Author: Nazem Mahmud Piash
Author-email: nazem.piash10@gmail.com
License: UNKNOWN
Platform: UNKNOWN
Classifier: Intended Audience :: Developers
Classifier: Programming Language :: Python :: 3
Classifier: License :: OSI Approved :: MIT License
Classifier: Operating System :: OS Independent
Classifier: Topic :: Software Development :: Internationalization
Requires-Python: >=3.5
License-File: LICENSE
Requires-Dist: requests
Requires-Dist: simplejson
